faster_fishers-0.1.1.dist-info/METADATA
faster_fishers-0.1.1.dist-info/WHEEL
faster_fishers/__init__.py
faster_fishers/faster_fishers.cpython-39-x86_64-linux-gnu.so
faster_fishers-0.1.1.dist-info/RECORD
