Metadata-Version: 2.1
Name: faster-fishers
Version: 0.1.1
Summary: Rust version of Scipy's Fisher exact test.
Author: Maxime Jacques <maxyme@outlook.com>
Author-email: Maxime Jacques <maxyme@outlook.com>
License: MIT
